sarasa/__init__.py
sarasa/activation_checkpoint.py
sarasa/checkpoint.py
sarasa/config.py
sarasa/metrics.py
sarasa/trainer.py
sarasa/utils.py
sarasa/data/__init__.py
sarasa/data/hf_datasets.py
sarasa/data/tokenizer.py
sarasa/models/__init__.py
sarasa/models/attention.py
sarasa/models/llama3.py
sarasa/models/nanochat_gpt.py
sarasa/models/utils.py
sarasa/optimizers/__init__.py
sarasa/optimizers/utils.py
sarasa-0.0.3.dist-info/METADATA
sarasa-0.0.3.dist-info/WHEEL
sarasa-0.0.3.dist-info/licenses/LICENSE
sarasa-0.0.3.dist-info/RECORD
