Metadata-Version: 2.4
Name: sarasa
Version: 0.0.3
Summary: Add your description here
License-File: LICENSE
Requires-Python: >=3.13
Requires-Dist: datasets>=4.5.0
Requires-Dist: loguru>=0.7.3
Requires-Dist: numpy>=2.4.1
Requires-Dist: rich>=14.2.0
Requires-Dist: tensorboard>=2.20.0
Requires-Dist: tokenizers>=0.22.2
Requires-Dist: tyro>=1.0.5
Provides-Extra: cpu
Requires-Dist: torch>=2.10.0; extra == 'cpu'
Provides-Extra: cu128
Requires-Dist: torch>=2.10.0; extra == 'cu128'
Provides-Extra: cu130
Requires-Dist: torch>=2.10.0; extra == 'cu130'
Provides-Extra: flash-attn
Requires-Dist: flash-attn-cute; extra == 'flash-attn'
